hello/__init__.py
hello_Heaven-0.0.1.dist-info/LICENSE
hello_Heaven-0.0.1.dist-info/METADATA
hello_Heaven-0.0.1.dist-info/WHEEL
hello_Heaven-0.0.1.dist-info/top_level.txt
hello_Heaven-0.0.1.dist-info/RECORD
