Metadata-Version: 2.1
Name: hello-Heaven
Version: 0.0.1
Summary: import hello hello.print
Home-page: UNKNOWN
Author: huang
Author-email: 1239863466@qq.com
License: UNKNOWN
Platform: UNKNOWN
Classifier: Programming Language :: Python :: 3
Classifier: License :: OSI Approved :: MIT License
Classifier: Operating System :: OS Independent
